pyPreservicaMSG/__init__.py
pyPreservicaMSG/__main__.py
pyPreservicaMSG/gui.py
pyPreservicaMSG/main.py
pyPreservicaMSG/parsemsg.py
pyPreservicaMSG/submission.py
pyPreservicaMSG-0.0.4.dist-info/METADATA
pyPreservicaMSG-0.0.4.dist-info/WHEEL
pyPreservicaMSG-0.0.4.dist-info/top_level.txt
pyPreservicaMSG-0.0.4.dist-info/RECORD
